{"cameraMode":{"drawMode":0,"name":"Shaded","section":"Shading Mode"},"sceneLighting":true,"audioPlay":false,"sceneViewState":{"m_AlwaysRefresh":false,"showFog":true,"showSkybox":true,"showFlares":true,"showImageEffects":true,"showParticleSystems":true,"showVisualEffectGraphs":true,"m_FxEnabled":true},"in2DMode":false,"pivot":{"x":2.867492198944092,"y":0.923095703125,"z":-9.408590316772461},"rotation":{"x":0.10760249197483063,"y":0.006950215436518192,"z":-0.0007912628934718669,"w":0.9942027926445007},"size":35.58574676513672,"orthographic":false}